{
    "QUI": {
        "id": "QUI",
        "nombre": "Profesorado en Química",
        "materias": [
            { "id": 1, "nombre": "Lectura y Escritura Académica", "anio": 1, "regular": [], "aprobada": [] },
            { "id": 2, "nombre": "Psicología Educacional", "anio": 1, "regular": [], "aprobada": [] },
            { "id": 3, "nombre": "Pedagogía", "anio": 1, "regular": [], "aprobada": [] },
            { "id": 4, "nombre": "Didáctica General", "anio": 1, "regular": [3], "aprobada": [] },
            { "id": 5, "nombre": "Química General", "anio": 1, "regular": [], "aprobada": [] },
            { "id": 6, "nombre": "Matemática", "anio": 1, "regular": [], "aprobada": [] },
            { "id": 7, "nombre": "Física Básica", "anio": 1, "regular": [6], "aprobada": [] },
            { "id": 8, "nombre": "Química Experimental I", "anio": 1, "regular": [], "aprobada": [] },
            { "id": 9, "nombre": "Lenguaje de la Química", "anio": 1, "regular": [], "aprobada": [] },
            { "id": 10, "nombre": "Práctica Profesional Docente I", "anio": 1, "regular": [], "aprobada": [] },
            { "id": 11, "nombre": "Historia y Política de la Ed. Arg.", "anio": 2, "regular": [3], "aprobada": [] },
            { "id": 12, "nombre": "Educación Sexual Integral", "anio": 2, "regular": [], "aprobada": [] },
            { "id": 13, "nombre": "Educación y TIC", "anio": 2, "regular": [], "aprobada": [] },
            { "id": 14, "nombre": "Química Orgánica", "anio": 2, "regular": [5, 9], "aprobada": [] },
            { "id": 15, "nombre": "Química Inorgánica", "anio": 2, "regular": [5, 9], "aprobada": [] },
            { "id": 16, "nombre": "Química Experimental II", "anio": 2, "regular": [5, 8], "aprobada": [] },
            { "id": 17, "nombre": "Didáctica de la Química I", "anio": 2, "regular": [4, 5, 8], "aprobada": [] },
            { "id": 18, "nombre": "Sujetos del Aprendizaje", "anio": 2, "regular": [2], "aprobada": [] },
            { "id": 19, "nombre": "Práctica Profesional Docente II", "anio": 2, "regular": [1, 4, 5, 10], "aprobada": [] },
            { "id": 20, "nombre": "Investigación Educativa", "anio": 3, "regular": [13], "aprobada": [1] },
            { "id": 21, "nombre": "Sociología de la Educación", "anio": 3, "regular": [11], "aprobada": [] },
            { "id": 22, "nombre": "Prob. Context. Cs. Naturales", "anio": 3, "regular": [9, 14], "aprobada": [5] },
            { "id": 23, "nombre": "Química Analítica", "anio": 3, "regular": [15], "aprobada": [5, 9] },
            { "id": 24, "nombre": "Físico Química", "anio": 3, "regular": [6, 7, 15], "aprobada": [5, 9] },
            { "id": 25, "nombre": "Química Experimental III", "anio": 3, "regular": [14, 16], "aprobada": [5, 8, 9] },
            { "id": 26, "nombre": "Didáctica de la Química II", "anio": 3, "regular": [14, 15, 16, 17, 18, 19], "aprobada": [4, 5, 8] },
            { "id": 27, "nombre": "Lab. Enseñanza de la Química", "anio": 3, "regular": [16, 17], "aprobada": [5, 8] },
            { "id": 28, "nombre": "Práctica Profesional Docente III", "anio": 3, "regular": [12, 15, 17, 18, 19], "aprobada": [1, 2, 3, 4, 5, 6, 7, 8, 9, 10] },
            { "id": 29, "nombre": "Filosofía de la Educación", "anio": 4, "regular": [21], "aprobada": [] },
            { "id": 30, "nombre": "UDI del CFG I", "anio": 4, "regular": [], "aprobada": [] },
            { "id": 31, "nombre": "UDI del CFG II", "anio": 4, "regular": [], "aprobada": [] },
            { "id": 32, "nombre": "Ctx. Sociohistóricos Química", "anio": 4, "regular": [14, 17], "aprobada": [5, 9, 15] },
            { "id": 33, "nombre": "Química Biológica", "anio": 4, "regular": [25], "aprobada": [5, 9, 14] },
            { "id": 34, "nombre": "Química Ambiental", "anio": 4, "regular": [14, 24], "aprobada": [5, 9, 15] },
            { "id": 35, "nombre": "UDI del CFE", "anio": 4, "regular": [], "aprobada": [] },
            { "id": 36, "nombre": "Inv. en Enseñanza de la Química", "anio": 4, "regular": [20, 26], "aprobada": [17] },
            { "id": 37, "nombre": "Práctica Prof. IV y Residencia", "anio": 4, "regular": [22, 26, 27], "aprobada": [11, 12, 13, 14, 15, 16, 17, 18, 19, 28] } 
        ]
    },
    "MAT": {
        "id": "MAT",
        "nombre": "Profesorado en Matemática",
        "materias": [
            { "id": 1, "nombre": "Lectura y Escritura Académica", "anio": 1, "regular": [], "aprobada": [] },
            { "id": 2, "nombre": "Psicología Educacional", "anio": 1, "regular": [], "aprobada": [] },
            { "id": 3, "nombre": "Pedagogía", "anio": 1, "regular": [], "aprobada": [] },
            { "id": 4, "nombre": "Didáctica General", "anio": 2, "regular": [3], "aprobada": [] },
            { "id": 5, "nombre": "El Quehacer Matemático", "anio": 1, "regular": [], "aprobada": [] },
            { "id": 6, "nombre": "Intr. Análisis de Funciones", "anio": 1, "regular": [], "aprobada": [] },
            { "id": 7, "nombre": "Álgebra Conjuntos Numéricos", "anio": 1, "regular": [], "aprobada": [] },
            { "id": 8, "nombre": "Geometría del Plano", "anio": 1, "regular": [], "aprobada": [] },
            { "id": 9, "nombre": "Práctica Profesional Docente I", "anio": 1, "regular": [], "aprobada": [] },
            { "id": 10, "nombre": "Historia y Pol. Ed. Arg.", "anio": 2, "regular": [3], "aprobada": [] },
            { "id": 11, "nombre": "Educación Sexual Integral", "anio": 2, "regular": [], "aprobada": [] },
            { "id": 12, "nombre": "Educación y TIC", "anio": 2, "regular": [], "aprobada": [] },
            { "id": 13, "nombre": "Didáctica de la Matemática I", "anio": 2, "regular": [4, 5, 6, 7, 8], "aprobada": [] },
            { "id": 14, "nombre": "Análisis Matemático", "anio": 2, "regular": [6, 7], "aprobada": [] },
            { "id": 15, "nombre": "Álgebra Lineal", "anio": 2, "regular": [5, 7, 8], "aprobada": [] },
            { "id": 16, "nombre": "Geometría del Espacio Euclideo y No Euclideo", "anio": 2, "regular": [8], "aprobada": [] },
            { "id": 17, "nombre": "Sujetos del Aprendizaje", "anio": 2, "regular": [2], "aprobada": [] },
            { "id": 18, "nombre": "Práctica Profesional Docente II", "anio": 2, "regular": [1, 4, 5, 6, 7, 8, 9], "aprobada": [] },
            { "id": 19, "nombre": "Investigación Educativa", "anio": 3, "regular": [12], "aprobada": [1] },
            { "id": 20, "nombre": "Sociología de la Educación", "anio": 3, "regular": [10], "aprobada": [] },
            { "id": 21, "nombre": "Análisis y Trat. de la Información", "anio": 3, "regular": [7], "aprobada": [6] },
            { "id": 22, "nombre": "Didáctica de la Matemática II", "anio": 3, "regular": [13, 14, 15, 16, 17, 18], "aprobada": [4, 6, 7, 8] },
            { "id": 23, "nombre": "Análisis Mat. en varias Variables", "anio": 3, "regular": [15, 16], "aprobada": [5, 7, 8] },
            { "id": 24, "nombre": "Estructuras Algebraicas", "anio": 3, "regular": [15, 16], "aprobada": [5, 7, 8] },
            { "id": 25, "nombre": "El lenguaje Alg. en Geometría", "anio": 3, "regular": [16], "aprobada": [8] },
            { "id": 26, "nombre": "Res. Problemas mediados por TIC", "anio": 3, "regular": [5, 6, 7, 8], "aprobada": [] },
            { "id": 27, "nombre": "Práctica Profesional Docente III", "anio": 3, "regular": [11, 13, 17, 18], "aprobada": [1, 2, 3, 4, 5, 6, 7, 8, 9] },
            { "id": 28, "nombre": "Filosofía de la Educación", "anio": 4, "regular": [20], "aprobada": [] },
            { "id": 29, "nombre": "UDI del CFG I", "anio": 4, "regular": [], "aprobada": [] },
            { "id": 30, "nombre": "UDI del CFG II", "anio": 4, "regular": [], "aprobada": [] },
            { "id": 31, "nombre": "Inv. en Educación Matemática", "anio": 4, "regular": [19, 22], "aprobada": [] },
            { "id": 32, "nombre": "Análisis y Diseño de la Ens. de la Matemática", "anio": 4, "regular": [14, 15, 16, 26], "aprobada": [5, 6, 7, 8] },
            { "id": 33, "nombre": "Const. Hist. y Epistemológica", "anio": 4, "regular": [23, 24, 25], "aprobada": [] },
            { "id": 34, "nombre": "UDI del CFE", "anio": 4, "regular": [], "aprobada": [] },
            { "id": 35, "nombre": "Práctica Prof. IV y Residencia", "anio": 4, "regular": [22], "aprobada": [10, 11, 12, 13, 14, 15, 16, 17, 18, 27] }
        ]
    },
        "FIS": {
        "id": "FIS",
        "nombre": "Profesorado en Física",
        "materias": [
            { "id": 1, "nombre": "Lectura y Escritura Académica", "anio": 1, "regular": [], "aprobada": [] },
            { "id": 2, "nombre": "Psicología Educacional", "anio": 1, "regular": [], "aprobada": [] },
            { "id": 3, "nombre": "Pedagogía", "anio": 1, "regular": [], "aprobada": [] },
            { "id": 4, "nombre": "Didáctica General", "anio": 2, "regular": [3], "aprobada": [] },
            { "id": 5, "nombre": "Mecánica", "anio": 1, "regular": [], "aprobada": [] },
            { "id": 6, "nombre": "Laboratorio de Mecánica", "anio": 1, "regular": [], "aprobada": [] },
            { "id": 7, "nombre": "Álgebra y Geométrica", "anio": 1, "regular": [], "aprobada": [] },
            { "id": 8, "nombre": "Análisis Matemático I", "anio": 1, "regular": [], "aprobada": [] },
            { "id": 9, "nombre": "Modelización Científica", "anio": 1, "regular": [], "aprobada": [] },
            { "id": 10, "nombre": "Práctica Profesional Docente I", "anio": 1, "regular": [3], "aprobada": [] },
            { "id": 11, "nombre": "Historia y Política de la Educación Argentina", "anio": 2, "regular": [3], "aprobada": [] },
            { "id": 12, "nombre": "Educación Sexual Integral", "anio": 2, "regular": [], "aprobada": [] },
            { "id": 13, "nombre": "Educación y TIC", "anio": 2, "regular": [], "aprobada": [] },
            { "id": 14, "nombre": "Termodinámica", "anio": 2, "regular": [5, 8], "aprobada": [] },
            { "id": 15, "nombre": "Laboratorio de Termodinámica", "anio": 2, "regular": [6], "aprobada": [] },
            { "id": 16, "nombre": "Didáctica de la Física I", "anio": 2, "regular": [4, 5, 9], "aprobada": [] },
            { "id": 17, "nombre": "Análisis Matemático II", "anio": 2, "regular": [7, 8], "aprobada": [] },
            { "id": 18, "nombre": "Sujetos del Aprendizaje", "anio": 2, "regular": [2], "aprobada": [] },
            { "id": 19, "nombre": "Práctica Profesional Docente II", "anio": 2, "regular": [1,2,3,4,5,6,7,8,9,10], "aprobada": [1] },
            { "id": 20, "nombre": "Investigación Educativa", "anio": 3, "regular": [13], "aprobada": [1] },
            { "id": 21, "nombre": "Sociología de la Educación", "anio": 3, "regular": [11], "aprobada": [] },
            { "id": 22, "nombre": "Producción de Textos Didácticos en Física", "anio": 3, "regular": [1, 16], "aprobada": [] },
            { "id": 23, "nombre": "Química Básica", "anio": 3, "regular": [5], "aprobada": [] },
            { "id": 24, "nombre": "Ondas", "anio": 3, "regular": [14, 17], "aprobada": [5, 7, 8] },
            { "id": 25, "nombre": "Electromagnetismo", "anio": 3, "regular": [14, 17], "aprobada": [5, 7, 8] },
            { "id": 26, "nombre": "Laboratorio de Electromagnetismo y Ondas", "anio": 3, "regular": [15], "aprobada": [6] },
            { "id": 27, "nombre": "Didáctica de la Física II", "anio": 3, "regular": [16, 18, 19], "aprobada": [4, 5] },
            { "id": 28, "nombre": "Práctica Profesional Docente III", "anio": 3, "regular": [11, 12, 13, 14, 15, 16, 17, 18, 19], "aprobada": [1, 2, 3, 4, 5, 6, 7, 8, 9, 10] },
            { "id": 29, "nombre": "Filosofía de la Educación", "anio": 4, "regular": [21], "aprobada": [] },
            { "id": 30, "nombre": "UDI del CFG I", "anio": 4, "regular": [], "aprobada": [] },
            { "id": 31, "nombre": "UDI del CFG II", "anio": 4, "regular": [], "aprobada": [] },
            { "id": 32, "nombre": "UDI del CFE", "anio": 4, "regular": [], "aprobada": [] },
            { "id": 33, "nombre": "Física Moderna y Contemporánea", "anio": 4, "regular": [24, 25], "aprobada": [5, 14] },
            { "id": 34, "nombre": "Investigación en Enseñanza de la Física", "anio": 4, "regular": [20, 27], "aprobada": [16] },
            { "id": 35, "nombre": "Laboratorio de Enseñanza de la Física", "anio": 4, "regular": [27, 26], "aprobada": [6, 15, 16] },
            { "id": 36, "nombre": "Contextos Socio Históricos de la Física", "anio": 4, "regular": [24, 25], "aprobada": [5, 14] },
            { "id": 37, "nombre": "Práctica Profesional Docente IV y Residencia", "anio": 4, "regular": [24, 25, 27], "aprobada": [11, 12, 13, 14, 15, 16, 17, 18, 19, 28] }
        ]
    },
    "TGC": {
        "id": "TGC",
        "nombre": "Tecnicatura Superior en Gestión Integrada de la Calidad",
        "materias": [
            { "id": 1, "nombre": "", "anio": 1, "regular": [], "aprobada": [] },
            { "id": 2, "nombre": "", "anio": 1, "regular": [], "aprobada": [] },
            { "id": 3, "nombre": "", "anio": 1, "regular": [], "aprobada": [] },
            { "id": 4, "nombre": "", "anio": 1, "regular": [], "aprobada": [] },
            { "id": 5, "nombre": "", "anio": 1, "regular": [], "aprobada": [] },
            { "id": 6, "nombre": "", "anio": 1, "regular": [], "aprobada": [] },
            { "id": 7, "nombre": "", "anio": 1, "regular": [], "aprobada": [] },
            { "id": 8, "nombre": "", "anio": 1, "regular": [], "aprobada": [] },
            { "id": 9, "nombre": "", "anio": 1, "regular": [], "aprobada": [] },
            { "id": 10, "nombre": "", "anio": 1, "regular": [], "aprobada": [] },
            { "id": 11, "nombre": "", "anio": 1, "regular": [], "aprobada": [] },
            { "id": 12, "nombre": "", "anio": 1, "regular": [], "aprobada": [] },
            { "id": 13, "nombre": "", "anio": 1, "regular": [], "aprobada": [] },
            { "id": 14, "nombre": "", "anio": 1, "regular": [], "aprobada": [] },
            { "id": 15, "nombre": "", "anio": 1, "regular": [], "aprobada": [] },
            { "id": 16, "nombre": "", "anio": 1, "regular": [], "aprobada": [] },
            { "id": 17, "nombre": "", "anio": 1, "regular": [], "aprobada": [] },
            { "id": 18, "nombre": "", "anio": 1, "regular": [], "aprobada": [] },
            { "id": 19, "nombre": "", "anio": 1, "regular": [], "aprobada": [] },
            { "id": 20, "nombre": "", "anio": 1, "regular": [], "aprobada": [] },
            { "id": 21, "nombre": "", "anio": 1, "regular": [], "aprobada": [] },
            { "id": 22, "nombre": "", "anio": 1, "regular": [], "aprobada": [] },
            { "id": 23, "nombre": "", "anio": 1, "regular": [], "aprobada": [] },
            { "id": 24, "nombre": "", "anio": 1, "regular": [], "aprobada": [] },
            { "id": 25, "nombre": "", "anio": 1, "regular": [], "aprobada": [] },
            { "id": 26, "nombre": "", "anio": 1, "regular": [], "aprobada": [] },
            { "id": 27, "nombre": "", "anio": 1, "regular": [], "aprobada": [] },
            { "id": 28, "nombre": "", "anio": 1, "regular": [], "aprobada": [] },
            { "id": 29, "nombre": "", "anio": 1, "regular": [], "aprobada": [] }
        ]
    },
    "TAP": {
        "id": "TAP",
        "nombre": "Tecnicatura Superior En Administración Pública Orientada Al Desarrollo Local",
        "materias": [
            { "id": 1, "nombre": " Práctica Profesional I (La Administración Pública)", "anio": 1, "regular": [], "aprobada": [] },
            { "id": 2, "nombre": "EDI 1", "anio": 1, "regular": [], "aprobada": [] },
            { "id": 3, "nombre": "Política, Sociedad y Estado ", "anio": 1, "regular": [], "aprobada": [] },
            { "id": 4, "nombre": "Tecnologías informáticas para la gestión ", "anio": 1, "regular": [], "aprobada": [] },
            { "id": 5, "nombre": "La administración pública ", "anio": 1, "regular": [], "aprobada": [] },
            { "id": 6, "nombre": "Metodología de la Investigación Social", "anio": 1, "regular": [], "aprobada": [] },
            { "id": 7, "nombre": "Estadística Básica", "anio": 1, "regular": [], "aprobada": [] },
            { "id": 8, "nombre": "Matemática Básica", "anio": 1, "regular": [], "aprobada": [] },
            { "id": 9, "nombre": "Práctica Profesional II (El Planeamiento Participativo)", "anio": 2, "regular": [1, 5, 6], "aprobada": [] },
            { "id": 10, "nombre": " Problemáticas Sociopolíticas Contemporáneas ", "anio": 2, "regular": [3], "aprobada": [] },
            { "id": 11, "nombre": "Contabilidad básica", "anio": 2, "regular": [8], "aprobada": [] },
            { "id": 12, "nombre": "EDI 2", "anio": 2, "regular": [], "aprobada": [] },
            { "id": 13, "nombre": " Políticas Públicas, Planeamiento Estratégico y Desarrollo Local", "anio": 2, "regular": [5], "aprobada": [] },
            { "id": 14, "nombre": "Derecho Administrativo", "anio": 2, "regular": [3], "aprobada": [] },
            { "id": 15, "nombre": " Economía local, regional y global", "anio": 2, "regular": [3], "aprobada": [] },
            { "id": 16, "nombre": " Práctica Profesional III (La intervención territorial)", "anio": 3, "regular": [9, 10, 11, 12, 13, 14, 15], "aprobada": [1, 2, 3, 4, 5, 6, 7, 8] },
            { "id": 17, "nombre": "Ética profesional ", "anio": 3, "regular": [14], "aprobada": [1, 2, 3, 4, 5, 6, 7, 8] },
            { "id": 18, "nombre": " Procesos Político – Económicos y el Mundo del Trabajo Actual", "anio": 3, "regular": [10, 15], "aprobada": [1, 2, 3, 4, 5, 6, 7, 8] },
            { "id": 19, "nombre": " Gestión Pública", "anio": 3, "regular": [13], "aprobada": [1, 2, 3, 4, 5, 6, 7, 8] },
            { "id": 20, "nombre": " Sistemas de Gestión de Personal ", "anio": 3, "regular": [14], "aprobada": [1, 2, 3, 4, 5, 6, 7, 8] },
            { "id": 21, "nombre": "Administración Financiera y presupuestaria del sector público", "anio": 3, "regular": [11, 15], "aprobada": [1, 2, 3, 4, 5, 6, 7, 8] },
            { "id": 22, "nombre": "Diseño y gestión de las Organizaciones", "anio": 3, "regular": [], "aprobada": [1, 2, 3, 4, 5, 6, 7, 8] },
            { "id": 23, "nombre": " Comunicación en las organizaciones ", "anio": 3, "regular": [], "aprobada": [1, 2, 3, 4, 5, 6, 7, 8] }
        ]
    },
      "PEF": {
        "id": "PEF",
        "nombre": "Profesorado de Educación Física",
        "materias": [
            { "id": 1, "nombre": "", "anio": 1, "regular": [], "aprobada": [] },
            { "id": 2, "nombre": "", "anio": 1, "regular": [], "aprobada": [] },
            { "id": 3, "nombre": "", "anio": 1, "regular": [], "aprobada": [] },
            { "id": 4, "nombre": "", "anio": 1, "regular": [], "aprobada": [] },
            { "id": 5, "nombre": "", "anio": 1, "regular": [], "aprobada": [] },
            { "id": 6, "nombre": "", "anio": 1, "regular": [], "aprobada": [] },
            { "id": 7, "nombre": "", "anio": 1, "regular": [], "aprobada": [] },
            { "id": 8, "nombre": "", "anio": 1, "regular": [], "aprobada": [] },
            { "id": 9, "nombre": "", "anio": 1, "regular": [], "aprobada": [] },
            { "id": 10, "nombre": "", "anio": 1, "regular": [], "aprobada": [] },
            { "id": 11, "nombre": "", "anio": 1, "regular": [], "aprobada": [] },
            { "id": 12, "nombre": "", "anio": 1, "regular": [], "aprobada": [] },
            { "id": 13, "nombre": "", "anio": 1, "regular": [], "aprobada": [] },
            { "id": 14, "nombre": "", "anio": 1, "regular": [], "aprobada": [] },
            { "id": 15, "nombre": "", "anio": 1, "regular": [], "aprobada": [] },
            { "id": 16, "nombre": "", "anio": 1, "regular": [], "aprobada": [] },
            { "id": 17, "nombre": "", "anio": 1, "regular": [], "aprobada": [] },
            { "id": 18, "nombre": "", "anio": 1, "regular": [], "aprobada": [] },
            { "id": 19, "nombre": "", "anio": 1, "regular": [], "aprobada": [] },
            { "id": 20, "nombre": "", "anio": 1, "regular": [], "aprobada": [] },
            { "id": 21, "nombre": "", "anio": 1, "regular": [], "aprobada": [] },
            { "id": 22, "nombre": "", "anio": 1, "regular": [], "aprobada": [] },
            { "id": 23, "nombre": "", "anio": 1, "regular": [], "aprobada": [] },
            { "id": 24, "nombre": "", "anio": 1, "regular": [], "aprobada": [] },
            { "id": 25, "nombre": "", "anio": 1, "regular": [], "aprobada": [] },
            { "id": 26, "nombre": "", "anio": 1, "regular": [], "aprobada": [] },
            { "id": 27, "nombre": "", "anio": 1, "regular": [], "aprobada": [] },
            { "id": 28, "nombre": "", "anio": 1, "regular": [], "aprobada": [] },
            { "id": 29, "nombre": "", "anio": 1, "regular": [], "aprobada": [] },
            { "id": 30, "nombre": "", "anio": 1, "regular": [], "aprobada": [] },
            { "id": 31, "nombre": "", "anio": 1, "regular": [], "aprobada": [] },
            { "id": 32, "nombre": "", "anio": 1, "regular": [], "aprobada": [] },
            { "id": 33, "nombre": "", "anio": 1, "regular": [], "aprobada": [] },
            { "id": 34, "nombre": "", "anio": 1, "regular": [], "aprobada": [] },
            { "id": 35, "nombre": "", "anio": 1, "regular": [], "aprobada": [] },
            { "id": 36, "nombre": "", "anio": 1, "regular": [], "aprobada": [] },
            { "id": 37, "nombre": "", "anio": 1, "regular": [], "aprobada": [] },
            { "id": 38, "nombre": "", "anio": 1, "regular": [], "aprobada": [] },
            { "id": 39, "nombre": "", "anio": 1, "regular": [], "aprobada": [] },
            { "id": 40, "nombre": "", "anio": 1, "regular": [], "aprobada": [] },
            { "id": 41, "nombre": "", "anio": 1, "regular": [], "aprobada": [] }
        ]
    },
"BIO": {
        "id": "BIO",
        "nombre": "Profesorado en Biología",
        "materias": [
            { "id": 1, "nombre": "Lectura y Escritura Académica", "anio": 1, "regular": [], "aprobada": [] },
            { "id": 2, "nombre": "Psicología Educacional", "anio": 1, "regular": [], "aprobada": [] },
            { "id": 3, "nombre": "Pedagogía", "anio": 1, "regular": [], "aprobada": [] },
            { "id": 4, "nombre": "Didáctica General", "anio": 2, "regular": [3], "aprobada": [] },
            { "id": 5, "nombre": "El Quehacer Matemático", "anio": 1, "regular": [], "aprobada": [] },
            { "id": 6, "nombre": "Intr. Análisis de Funciones", "anio": 1, "regular": [], "aprobada": [] },
            { "id": 7, "nombre": "Álgebra Conjuntos Numéricos", "anio": 1, "regular": [], "aprobada": [] },
            { "id": 8, "nombre": "Geometría del Plano", "anio": 1, "regular": [], "aprobada": [] },
            { "id": 9, "nombre": "Práctica Profesional Docente I", "anio": 1, "regular": [], "aprobada": [] }
        ]
    }
}





